optimized_smt/__init__.py
optimized_smt/json.py
optimized_smt/node.py
optimized_smt/optimized_smt.py
optimized_smt/smt_proof.py
optimized_smt/utility.py
optimized_smt-1.0.2b0.dist-info/METADATA
optimized_smt-1.0.2b0.dist-info/WHEEL
optimized_smt-1.0.2b0.dist-info/RECORD
